[
  {
    "id": 1,
    "name": "Student Visa",
    "price": "$500",
    "description": "Students can get F1 students visa,J1 exchange visitor visa and also non-academic visa from me!",
    "img": "https://fastwpdemo.com/newwp/immigo/wp-content/uploads/2022/02/visa-1.jpg"
  },
  {
    "id": 2,
    "name": "Residence Visa",
    "price": "$600",
    "description": "Residence visa now-a-days hardly offering by county,but with some of my tips you can easily persue it!",
    "img": "https://fastwpdemo.com/newwp/immigo/wp-content/uploads/2022/02/visa-2.jpg"
  },
  {
    "id": 3,
    "name": "Business Visa",
    "price": "$750",
    "description": "I provide Business Visa,Employment Visa and Project Visa as well. ",
    "img": "https://fastwpdemo.com/newwp/immigo/wp-content/uploads/2022/02/visa-3.jpg"
  },
  {
    "id": 4,
    "name": "Tourist Visa",
    "price": "$980",
    "description": "If you are ready to explore the world,I am always here to help you",
    "img": "https://fastwpdemo.com/newwp/immigo/wp-content/uploads/2022/02/visa-4.jpg"
  }
]
